lanoel/__init__.py
lanoel/__main__.py
lanoel/cli.py
lanoel/lanoel.py
lanoel/utils.py
lanoel-0.1.2.dist-info/entry_points.txt
lanoel-0.1.2.dist-info/METADATA
lanoel-0.1.2.dist-info/WHEEL
lanoel-0.1.2.dist-info/RECORD
