Metadata-Version: 2.1
Name: lanoel
Version: 0.1.2
Summary: A Secret Santa generator for groups of people.
Author: felixilgatto
Author-email: essais2615@gmail.com
Requires-Python: >=3.12,<4.0
Classifier: Programming Language :: Python :: 3
Classifier: Programming Language :: Python :: 3.12
